realeyes.demographic_estimation-1.1.0.dist-info/WHEEL
realeyes.demographic_estimation-1.1.0.dist-info/top_level.txt
realeyes.demographic_estimation-1.1.0.dist-info/RECORD
realeyes.demographic_estimation-1.1.0.dist-info/METADATA
realeyes/demographic_estimation/__init__.py
realeyes/demographic_estimation/cpp.cpython-312-x86_64-linux-gnu.so
realeyes/demographic_estimation/py.typed
realeyes/demographic_estimation/libDemographicEstimationLibrary.so
realeyes/demographic_estimation/__init__.pyi
