Metadata-Version: 2.1
Name: realeyes.demographic-estimation
Version: 1.1.0
Summary: Demographic Estimation Library from RealEyes
Author: Realeyes
Author-email: daniel@realeyesit.com
Requires-Dist: numpy >=1.10.0
